errorcalc/__init__.py
errorcalc/errors.py
errorcalc/latex_containers.py
pyerrorcalc-1.0.1.dist-info/METADATA
pyerrorcalc-1.0.1.dist-info/WHEEL
pyerrorcalc-1.0.1.dist-info/top_level.txt
pyerrorcalc-1.0.1.dist-info/RECORD
